python_watcher-15.0.0.data/data/etc/apache2/watcher
python_watcher-15.0.0.data/data/etc/watcher/README-watcher.conf.txt
python_watcher-15.0.0.data/data/etc/watcher/oslo-config-generator/watcher.conf
python_watcher-15.0.0.data/data/etc/watcher/oslo-policy-generator/watcher-policy-generator.conf
python_watcher-15.0.0.data/scripts/watcher-api-wsgi
watcher/__init__.py
watcher/_i18n.py
watcher/eventlet.py
watcher/version.py
watcher/api/__init__.py
watcher/api/acl.py
watcher/api/app.py
watcher/api/app.wsgi
watcher/api/config.py
watcher/api/hooks.py
watcher/api/scheduling.py
watcher/api/wsgi.py
watcher/api/controllers/__init__.py
watcher/api/controllers/base.py
watcher/api/controllers/link.py
watcher/api/controllers/rest_api_version_history.rst
watcher/api/controllers/root.py
watcher/api/controllers/v1/__init__.py
watcher/api/controllers/v1/action.py
watcher/api/controllers/v1/action_plan.py
watcher/api/controllers/v1/audit.py
watcher/api/controllers/v1/audit_template.py
watcher/api/controllers/v1/collection.py
watcher/api/controllers/v1/data_model.py
watcher/api/controllers/v1/efficacy_indicator.py
watcher/api/controllers/v1/goal.py
watcher/api/controllers/v1/scoring_engine.py
watcher/api/controllers/v1/service.py
watcher/api/controllers/v1/strategy.py
watcher/api/controllers/v1/types.py
watcher/api/controllers/v1/utils.py
watcher/api/controllers/v1/versions.py
watcher/api/controllers/v1/webhooks.py
watcher/api/middleware/__init__.py
watcher/api/middleware/auth_token.py
watcher/api/middleware/parsable_error.py
watcher/applier/__init__.py
watcher/applier/base.py
watcher/applier/default.py
watcher/applier/manager.py
watcher/applier/rpcapi.py
watcher/applier/sync.py
watcher/applier/action_plan/__init__.py
watcher/applier/action_plan/base.py
watcher/applier/action_plan/default.py
watcher/applier/actions/__init__.py
watcher/applier/actions/base.py
watcher/applier/actions/change_node_power_state.py
watcher/applier/actions/change_nova_service_state.py
python_watcher-15.0.0.dist-info/AUTHORS
python_watcher-15.0.0.dist-info/LICENSE
python_watcher-15.0.0.dist-info/METADATA
python_watcher-15.0.0.dist-info/WHEEL
python_watcher-15.0.0.dist-info/entry_points.txt
python_watcher-15.0.0.dist-info/pbr.json
python_watcher-15.0.0.dist-info/top_level.txt
python_watcher-15.0.0.dist-info/RECORD
