Metadata-Version: 2.1
Name: python-watcher
Version: 15.0.0
Summary: OpenStack Watcher provides a flexible and scalable resource optimization service for multi-tenant OpenStack-based clouds.
Home-page: https://docs.openstack.org/watcher/latest/
Author: OpenStack
Author-email: openstack-discuss@lists.openstack.org
Classifier: Environment :: OpenStack
Classifier: Intended Audience :: Information Technology
Classifier: Intended Audience :: System Administrators
Classifier: License :: OSI Approved :: Apache Software License
Classifier: Operating System :: POSIX :: Linux
Classifier: Programming Language :: Python
Classifier: Programming Language :: Python :: Implementation :: CPython
Classifier: Programming Language :: Python :: 3 :: Only
Classifier: Programming Language :: Python :: 3
Classifier: Programming Language :: Python :: 3.10
Classifier: Programming Language :: Python :: 3.11
Classifier: Programming Language :: Python :: 3.12
Requires-Python: >=3.10
License-File: LICENSE
License-File: AUTHORS
Requires-Dist: apscheduler >=3.5.1
Requires-Dist: debtcollector >=1.2.0
Requires-Dist: eventlet >=0.27.0
Requires-Dist: jsonpatch >=1.21
Requires-Dist: keystoneauth1 >=3.4.0
Requires-Dist: jsonschema >=3.2.0
Requires-Dist: keystonemiddleware >=4.21.0
Requires-Dist: lxml >=4.5.1
Requires-Dist: croniter >=0.3.20
Requires-Dist: os-resource-classes >=0.4.0
Requires-Dist: oslo.concurrency >=3.26.0
Requires-Dist: oslo.cache >=1.29.0
Requires-Dist: oslo.config >=6.8.0
Requires-Dist: oslo.context >=2.21.0
Requires-Dist: oslo.db >=4.44.0
Requires-Dist: oslo.i18n >=3.20.0
Requires-Dist: oslo.log >=3.37.0
Requires-Dist: oslo.messaging >=14.1.0
Requires-Dist: oslo.policy >=4.5.0
Requires-Dist: oslo.reports >=1.27.0
Requires-Dist: oslo.serialization >=2.25.0
Requires-Dist: oslo.service[threading] >=4.2.1
Requires-Dist: oslo.upgradecheck >=1.3.0
Requires-Dist: oslo.utils >=7.0.0
Requires-Dist: oslo.versionedobjects >=1.32.0
Requires-Dist: PasteDeploy >=1.5.2
Requires-Dist: pbr >=3.1.1
Requires-Dist: pecan >=1.3.2
Requires-Dist: PrettyTable >=0.7.2
Requires-Dist: gnocchiclient >=7.0.1
Requires-Dist: python-cinderclient >=3.5.0
Requires-Dist: python-glanceclient >=2.9.1
Requires-Dist: python-keystoneclient >=3.15.0
Requires-Dist: python-neutronclient >=6.7.0
Requires-Dist: python-novaclient >=14.1.0
Requires-Dist: python-observabilityclient >=1.1.0
Requires-Dist: python-openstackclient >=3.14.0
Requires-Dist: python-ironicclient >=2.5.0
Requires-Dist: SQLAlchemy >=1.2.5
Requires-Dist: stevedore >=1.28.0
Requires-Dist: taskflow >=3.8.0
Requires-Dist: WebOb >=1.8.5
Requires-Dist: WSME >=0.9.2
Requires-Dist: networkx >=2.4
Requires-Dist: microversion-parse >=0.2.1
Requires-Dist: futurist >=1.8.0
Provides-Extra: monasca
Requires-Dist: python-monascaclient >=1.12.0 ; extra == 'monasca'
